dss/__init__.py
dss/annot.py
dss/cli.py
dss/data.py
dss/evaluate.py
dss/event_utils.py
dss/io.py
dss/make_dataset.py
dss/models.py
dss/npy_dir.py
dss/predict.py
dss/pulse_utils.py
dss/segment_utils.py
dss/train.py
dss/train_transfer.py
dss/utils.py
dss/utils_plot.py
dss/kapre/LICENSE.txt
dss/kapre/README.md
dss/kapre/__init__.py
dss/kapre/augmentation.py
dss/kapre/backend.py
dss/kapre/backend_keras.py
dss/kapre/filterbank.py
dss/kapre/time_frequency.py
dss/kapre/utils.py
dss/tcn/LICENSE
dss/tcn/README.md
dss/tcn/__init__.py
dss/tcn/tcn.py
dss/tcn/tcn_new.py
deepss-0.19.1.dist-info/entry_points.txt
deepss-0.19.1.dist-info/WHEEL
deepss-0.19.1.dist-info/METADATA
deepss-0.19.1.dist-info/RECORD
